{
  "actionType" : "NEWT",
  "assetClass" : "CURR",
  "beneficiary1" : "W22LROWP2IHZNBB6K528",
  "beneficiary1IdentifierTypeIndicator" : true,
  "bookingLocation" : "GB",
  "cleared" : "N",
  "collateralPortfolioIndicator" : false,
  "confirmed" : "ECNF",
  "contractType" : "FORW",
  "corporateSectorOfTheCounterparty2" : [ "INVF" ],
  "counterparty1" : "W22LROWP2IHZNBB6K528",
  "counterparty2" : "MXKQVM4U1OHBQWFPG196",
  "counterparty2IdentifierFormat" : "Lei",
  "counterparty2IdentifierType" : true,
  "cryptoAssetUnderlyingIndicator" : false,
  "deliveryType" : "PHYS",
  "effectiveDate" : "2020-11-10",
  "entityResponsibleForReporting" : "W22LROWP2IHZNBB6K528",
  "eventIdentifier" : "envuatuatExt194fb4f6f93f94a52bec31af33e3ee894",
  "eventTimestamp" : "2020-11-10T05:44:46Z",
  "eventType" : "TRAD",
  "exchangeRate" : 1.06,
  "exchangeRateBasis" : "EUR/USD",
  "executionTimestamp" : "2020-11-10T05:44:46Z",
  "expirationDate" : "2022-03-25",
  "finalContractualSettlementDate" : "2022-03-25",
  "intragroup" : false,
  "leg1" : {
    "direction2" : "MAKE",
    "notionalAmount" : 15240,
    "notionalCurrency" : "EUR"
  },
  "leg2" : {
    "direction2" : "TAKE",
    "notionalAmount" : 16154.4,
    "notionalCurrency" : "USD"
  },
  "natureOfCounterparty2" : "F",
  "nonStandardizedTermIndicator" : false,
  "reportSubmittingEntityID" : "W22LROWP2IHZNBB6K528",
  "reportingTimestamp" : "2024-04-29T00:00:00Z",
  "secondaryTransactionIdentifier" : "FXFORWARDEXPARTYPA01",
  "technicalRecordId" : "HKMA-W22LROWP2IHZNBB6K528-MXKQVM4U1OHBQWFPG196-2020-11-10T05:44:46Z",
  "uniqueTransactionIdentifierProprietary" : "FXFORWARDEXPARTYPA01",
  "uniqueTransactionIdentifierProprietarySchemeName" : "UTI-TID"
}