{
  "actionType" : "NEWT",
  "cleared" : "N",
  "counterparty1" : "DUMMYLEI012345678901",
  "counterparty2" : "DUMMYLEI012345678903",
  "counterparty2IdentifierSource" : "LEID",
  "counterparty2IdentifierType" : true,
  "customBasketIndicator" : false,
  "dtccAdditionalFields" : {
    "messageID" : "DTDApproved2381994503EMIRRiskNewNewInterest2024-04-29T00:00Z",
    "messageTypePPD" : "RT",
    "primaryAssetClass" : "InterestRate",
    "submittedForParty" : "DUMMYLEI012345678901",
    "submittingPartyIDType" : "LEI",
    "tradeParty1IDType" : "LEI",
    "tradeParty1ReportingDestination" : [ "CA.AB.ASC" ],
    "tradeParty2ExecutionAgentID" : "DUMMYLEI012345678905",
    "tradeParty2ExecutionAgentIDType" : "LEI",
    "versionPPD" : "PPD1.0"
  },
  "effectiveDate" : "2020-07-29",
  "eventTimestamp" : "2021-03-31T07:39:54Z",
  "eventType" : "TRAD",
  "executionTimestamp" : "2021-03-31T07:39:42Z",
  "expirationDate" : "2028-07-29",
  "leg1" : {
    "fixedRate" : 0.02085,
    "notionalAmount" : 30000000,
    "notionalCurrency" : "USD",
    "periodicPayment" : {
      "fixedRateDayCountConvention" : "A020",
      "fixedRatePaymentFrequencyPeriod" : "YEAR",
      "fixedRatePaymentFrequencyPeriodMultiplier" : 1
    }
  },
  "leg2" : {
    "notionalAmount" : 30000000,
    "notionalCurrency" : "USD",
    "periodicPayment" : {
      "floatingRatePaymentFrequencyPeriod" : "YEAR",
      "floatingRatePaymentFrequencyPeriodMultiplier" : 1,
      "floatingRateResetFrequencyMultiplier" : 1,
      "floatingRateResetFrequencyPeriod" : "YEAR"
    }
  },
  "nonReportable" : {
    "instrumentType" : "Swap",
    "notionalSchedule" : "Constant",
    "preUpiData" : {
      "request" : {
        "Attributes" : {
          "DeliveryType" : "PHYS",
          "NotionalCurrency" : "USD",
          "NotionalSchedule" : "Constant",
          "ReferenceRateTermUnit" : "YEAR",
          "UnderlierID" : "USA-CPI-U",
          "UnderlierIDSource" : "FPML"
        },
        "Header" : {
          "AssetClass" : "Rates",
          "InstrumentType" : "Swap",
          "Level" : "UPI",
          "UseCase" : "Inflation_Fixed_Float_YoY"
        }
      },
      "requestType" : "ProductRequest"
    }
  },
  "nonStandardizedTermIndicator" : false,
  "packageIndicator" : false,
  "platformIdentifier" : "XXXX",
  "reportSubmittingEntityID" : "DUMMYLEI012345678901",
  "reportingTimestamp" : "2024-04-29T00:00:00Z",
  "uniqueTransactionIdentifier" : "IRINFLATIONFIXEDFL03"
}