{
  "actionType" : "NEWT",
  "assetClass" : "CURR",
  "cleared" : "N",
  "clearingObligation" : "FLSE",
  "clearingThresholdOfCounterparty1" : true,
  "clearingThresholdOfCounterparty2" : true,
  "collateralPortfolioIndicator" : false,
  "confirmationTimestamp" : "2020-12-01T13:13:08Z",
  "confirmed" : "ECNF",
  "contractType" : "OPTN",
  "corporateSectorOfTheCounterparty1" : [ "AIFD" ],
  "corporateSectorOfTheCounterparty2" : [ "CDTI" ],
  "counterparty1" : "W22LROWP2IHZNBB6K528",
  "counterparty2" : "MXKQVM4U1OHBQWFPG196",
  "counterparty2IdentifierType" : true,
  "cryptoAssetUnderlyingIndicator" : false,
  "deliveryType" : "CASH",
  "direction1" : "BYER",
  "effectiveDate" : "2020-12-01",
  "entityResponsibleForReporting" : "W22LROWP2IHZNBB6K528",
  "eventDate" : "2020-12-01",
  "eventType" : "TRAD",
  "exchangeRateBasis" : "BRL/USD",
  "executionTimestamp" : "2020-12-01T13:13:08Z",
  "expirationDate" : "2021-01-12",
  "finalContractualSettlementDate" : "2021-01-14",
  "forwardExchangeRate" : 1.3,
  "intragroup" : false,
  "leg1" : {
    "notionalAmount" : 10000000,
    "notionalCurrency" : "BRL",
    "settlementCurrency" : "USD"
  },
  "leg2" : {
    "notionalAmount" : 13000000,
    "notionalCurrency" : "USD"
  },
  "level" : "TCTN",
  "masterAgreementType" : "ISDA",
  "masterAgreementVersion" : 2002,
  "natureOfCounterparty1" : "F",
  "natureOfCounterparty2" : "F",
  "optionPremiumAmount" : 60,
  "optionPremiumCurrency" : "USD",
  "optionPremiumPaymentDate" : "2020-12-03",
  "optionStyle" : "EURO",
  "optionType" : "OTHR",
  "productClassification" : "HFTXVC",
  "ptrr" : false,
  "reportSubmittingEntityID" : "W22LROWP2IHZNBB6K528",
  "reportingObligationOfTheCounterparty2" : true,
  "reportingTimestamp" : "2024-04-29T00:00:00Z",
  "strikePrice" : {
    "monetary" : 1.3
  },
  "strikePriceCurrency" : "BRL/USD",
  "strikePriceNotation" : "Monetary",
  "uniqueTransactionIdentifier" : "FXNDOEXEUROPEANXML02",
  "venueOfExecution" : "XXXX"
}