<document xmlns="http://www.dtcc.com/DTCC/rds-1" xmlns:xsi="http://www.w3.org/2001/XMLSchema-instance">
  <submission>
    <header>
      <sender>W22LROWP2IHZNBB6K528</sender>
      <documentTrackingId>envuatuatExt1b45f8f29f8024fcf882f22f0287de1bc2024-04-29T00:00Z</documentTrackingId>
      <documentCreationTimestamp>2024-04-29T00:00:00Z</documentCreationTimestamp>
    </header>
    <core>
      <latestExecutionDatetime>2020-07-06T03:58:14Z</latestExecutionDatetime>
      <messageId>envuatuatExt1b45f8f29f8024fcf882f22f0287de1bc2024-04-29T00:00Z</messageId>
      <messageType>RT</messageType>
      <primaryAssetClass>ForeignExchange</primaryAssetClass>
      <submittedForParty>W22LROWP2IHZNBB6K528</submittedForParty>
      <submittingPartyId>W22LROWP2IHZNBB6K528</submittingPartyId>
      <submittingPartyIdType>LEI</submittingPartyIdType>
      <tradeParty1Id>W22LROWP2IHZNBB6K528</tradeParty1Id>
      <tradeParty1IdType>LEI</tradeParty1IdType>
      <tradeParty1ReportingDestination>CA.AB.ASC</tradeParty1ReportingDestination>
      <tradeParty1TransactionId>FXVANILLAOPTIONEXE01</tradeParty1TransactionId>
      <tradeParty2Id>MXKQVM4U1OHBQWFPG196</tradeParty2Id>
      <tradeParty2IdType>LEID</tradeParty2IdType>
      <utiId>FXVANILLAOPTIONEXE02</utiId>
      <reportingTimestamp>2024-04-29T00:00:00Z</reportingTimestamp>
      <noaActionType>NEWT</noaActionType>
      <noaEventType>TRAD</noaEventType>
    </core>
    <harmonizedData>
      <exchangeRate>6.9425</exchangeRate>
      <exchangeRateBasisCurrency1>USD</exchangeRateBasisCurrency1>
      <exchangeRateBasisCurrency2>CNY</exchangeRateBasisCurrency2>
      <clearingStatus>N</clearingStatus>
      <nonStandardTradeIndicator>false</nonStandardTradeIndicator>
      <notionalAmount1>20827500</notionalAmount1>
      <notionalCurrency1>CNY</notionalCurrency1>
      <notionalAmount2>3000000</notionalAmount2>
      <notionalCurrency2>USD</notionalCurrency2>
      <premiumAmount>40723.8</premiumAmount>
      <premiumCurrency>CNY</premiumCurrency>
      <version>PPD1.0</version>
      <originalExecutionTimestamp>2020-07-06T03:58:14Z</originalExecutionTimestamp>
      <strikePrice>6.9425</strikePrice>
      <strikePriceCurrency>USD</strikePriceCurrency>
      <customBasketIndicator>false</customBasketIndicator>
      <noaActionType>NEWT</noaActionType>
      <eventType>TRAD</eventType>
      <cdeCallAmountLeg1>20827500</cdeCallAmountLeg1>
      <cdeCallCurrencyLeg1>CNY</cdeCallCurrencyLeg1>
      <cdePutAmountLeg1>3000000</cdePutAmountLeg1>
      <cdePutCurrencyLeg1>USD</cdePutCurrencyLeg1>
      <packageIndicator>false</packageIndicator>
      <cdeStrikePriceNotation>1</cdeStrikePriceNotation>
      <cdeFirstExerciseDate>2020-09-29</cdeFirstExerciseDate>
      <cdeEffectiveDate>2020-07-06</cdeEffectiveDate>
      <cdeExpirationDate>2020-09-29</cdeExpirationDate>
      <cdePlatformIdentifier>BILT</cdePlatformIdentifier>
    </harmonizedData>
    <harmonizedRepeatableData>
      <tradeParty1ReportingDestination>CA.AB.ASC</tradeParty1ReportingDestination>
    </harmonizedRepeatableData>
  </submission>
</document>
