{
  "id" : "pipeline-projection-asic-trade-report-to-iso20022",
  "name" : "Asic Trade Report To Iso20022",
  "transform" : {
    "type" : "PROJECTION",
    "function" : "drr.projection.iso20022.asic.rewrite.trade.functions.Project_ASICTradeReportToIso20022",
    "inputType" : "drr.regulation.asic.rewrite.trade.ASICTransactionReport",
    "outputType" : "iso20022.auth030.asic.Document"
  },
  "upstreamPipelineId" : "pipeline-report-asic-trade",
  "outputSerialisation" : {
    "format" : "XML",
    "configPath" : "xml-config/auth030-asic-rosetta-xml-config.json"
  }
}