{
  "actionType" : "NEWT",
  "assetClass" : "EQUI",
  "cleared" : "N",
  "clearingObligation" : "FLSE",
  "clearingThresholdOfCounterparty1" : true,
  "clearingThresholdOfCounterparty2" : true,
  "collateralPortfolioIndicator" : false,
  "confirmed" : "NCNF",
  "contractType" : "OPTN",
  "corporateSectorOfTheCounterparty1" : [ "INVF" ],
  "corporateSectorOfTheCounterparty2" : [ "INUN" ],
  "counterparty1" : "DUMMY0000000000LEI01",
  "counterparty2" : "DUMMY0000000000LEI02",
  "counterparty2IdentifierType" : true,
  "cryptoAssetUnderlyingIndicator" : false,
  "direction1" : "BYER",
  "effectiveDate" : "2020-09-17",
  "entityResponsibleForReporting" : "DUMMY0000000000LEI01",
  "eventDate" : "2020-09-17",
  "eventType" : "TRAD",
  "executionTimestamp" : "2020-09-17T16:25:19Z",
  "expirationDate" : "2020-10-16",
  "finalContractualSettlementDate" : "2020-10-16",
  "intragroup" : false,
  "leg1" : {
    "totalNotionalQuantity" : 9999999999999999999999999
  },
  "level" : "TCTN",
  "masterAgreementType" : "ISDA",
  "masterAgreementVersion" : 2002,
  "natureOfCounterparty1" : "F",
  "natureOfCounterparty2" : "F",
  "optionPremiumAmount" : 48011.94,
  "optionPremiumCurrency" : "EUR",
  "optionPremiumPaymentDate" : "2020-09-21",
  "optionStyle" : "AMER",
  "optionType" : "CALL",
  "productClassification" : "HEBPXX",
  "ptrr" : false,
  "reportSubmittingEntityID" : "DUMMY0000000000LEI01",
  "reportingObligationOfTheCounterparty2" : true,
  "reportingTimestamp" : "2024-04-29T00:00:00Z",
  "strikePrice" : {
    "monetary" : 128
  },
  "strikePriceCurrency" : "EUR",
  "strikePriceNotation" : "Monetary",
  "underlyingIdentificationType" : "B",
  "uniqueTransactionIdentifier" : "EQUITYOPTIONPRICER01",
  "venueOfExecution" : "XXXX"
}